glfw/__init__.py
glfw/glfw3.h
glfw_cffi-0.1.7.dist-info/DESCRIPTION.rst
glfw_cffi-0.1.7.dist-info/METADATA
glfw_cffi-0.1.7.dist-info/metadata.json
glfw_cffi-0.1.7.dist-info/RECORD
glfw_cffi-0.1.7.dist-info/top_level.txt
glfw_cffi-0.1.7.dist-info/WHEEL
