Metadata-Version: 2.0
Name: glfw-cffi
Version: 0.1.7
Summary: Foreign Function Interface wrapper for GLFW v3.x
Home-page: https://github.com/brianbruggeman/glfw-cffi.git
Author: Brian Bruggeman
Author-email: brian.m.bruggeman@gmail.com
License: Apache 2.0
Keywords: GLFW,CFFI
Platform: UNKNOWN
Classifier: Topic :: Multimedia :: Graphics
Classifier: Topic :: Multimedia :: Graphics :: 3D Rendering
Classifier: Topic :: Multimedia :: Graphics :: Viewers
Classifier: Topic :: Software Development :: User Interfaces
Classifier: Intended Audience :: Developers
Classifier: Intended Audience :: Education
Classifier: Development Status :: 3 - Alpha
Classifier: License :: OSI Approved :: GNU General Public License (GPL)
Classifier: Operating System :: OS Independent
Classifier: Programming Language :: Python :: 2.7
Classifier: Programming Language :: Python :: 3.5
Classifier: Programming Language :: Python :: Implementation :: CPython
Classifier: Programming Language :: Python :: Implementation :: PyPy
Requires-Dist: cffi
Requires-Dist: pyopengl
Requires-Dist: docopt
Requires-Dist: freetype-py
Requires-Dist: numpy
